[
  {
    "checklist_order": "1",
    "handoff_status": "tokenization_gain_frontier_fill_handoff_ready",
    "queue_status": "queue_complete",
    "adapted_and_aligned_count": "5",
    "case_count": "5",
    "prerequisite_artifact": "results/figures/meeteval_tokenization_gain_to_frontier_fill_handoff.md",
    "receipt_target": "results/figures/frontier_execution_receipt_fill_execution_operator_brief.md",
    "checklist_goal": "Verify tokenization-to-fill handoff before opening the frontier fill operator brief.",
    "bridge_note": "Tokenization-to-fill handoff reports handoff_status=tokenization_gain_frontier_fill_handoff_ready with queue_status=queue_complete at 5/5 adapted-and-aligned cases.",
    "next_gate": "Confirm this bridge before opening the frontier fill operator brief."
  }
]