[
  {
    "checklist_order": "1",
    "readiness_status": "preflight_ready",
    "case_id": "NoOverlap",
    "preflight_pass": "True",
    "prerequisite_artifact": "results/figures/speaker_profile_embedding_trial_execution_preflight_readiness.md",
    "receipt_target": "results/tables/speaker_profile_embedding_trial_execution_receipt.json",
    "checklist_goal": "Verify execution preflight readiness for NoOverlap before opening the execution receipt.",
    "bridge_note": "Preflight readiness reports readiness_status=preflight_ready with preflight_pass=True; confirm swapped-bias proxy context before advancing to voiceprint execution receipt.",
    "next_gate": "Confirm this bridge before opening the embedding trial execution receipt target."
  }
]